<annotation>
	<folder>New E</folder>
	<filename>IMG_20181103_141058_1.jpg</filename>
	<path>C:\Users\User\Downloads\versity\New E\IMG_20181103_141058_1.jpg</path>
	<source>
		<database>Unknown</database>
	</source>
	<size>
		<width>1534</width>
		<height>907</height>
		<depth>3</depth>
	</size>
	<segmented>0</segmented>
	<object>
		<name>e</name>
		<pose>Unspecified</pose>
		<truncated>0</truncated>
		<difficult>0</difficult>
		<bndbox>
			<xmin>863</xmin>
			<ymin>239</ymin>
			<xmax>1264</xmax>
			<ymax>799</ymax>
		</bndbox>
	</object>
</annotation>
